nonebot_plugin_qbittorrent_manager/__init__.py
nonebot_plugin_qbittorrent_manager/command.py
nonebot_plugin_qbittorrent_manager/config.py
nonebot_plugin_qbittorrent_manager/draw.py
nonebot_plugin_qbittorrent_manager/qb_api.py
nonebot_plugin_qbittorrent_manager/tools.py
nonebot_plugin_qbittorrent_manager-1.1.5.dist-info/METADATA
nonebot_plugin_qbittorrent_manager-1.1.5.dist-info/WHEEL
nonebot_plugin_qbittorrent_manager-1.1.5.dist-info/licenses/LICENSE
nonebot_plugin_qbittorrent_manager-1.1.5.dist-info/RECORD
